{"index.md":"cf9c00ea","html_rearrange-and-redraw.md":"c9e16d22","html_index.md":"c91e6f24","cssstudy_cssoptimization.md":"a3d1cf0a","about_index.md":"49799c2d","html_semantictagging.md":"253a4dea","vuestudy_1.md":"e0f5b8b3","jsstudy_3-7-objectdeconstruction.md":"3ef66026","jsstudy_konweltype.md":"03b0c315","musicrelex_index.md":"5574f60e","personal-project-review_个人项目难点总结复盘.md":"b6eea16d","jsstudy_fd-and-jieliu.md":"84553e0a","develop-common-requirements_index.md":"c13af064","cssstudy_boxmodel.md":"8633e206","vscodechajian_index.md":"f1d1ddca","cssstudy_scss-study.md":"10990b46","ajaxstudy_index.md":"c91dcf33","jslibrary_particles-js.md":"52dbaf30","jsstudy_array.md":"5cbc3128","vuestudy_vue.js 设计与实现.md":"8171e736","jsstudy_你不知道的javascript（上卷）.md":"8063f5c0","cssstudy_cssdaoying.md":"0e223668","weblist_websocket.md":"45132d6b","cssstudy_boxjuzhong.md":"25b9e9a3","toolweb_index.md":"e26ac223","jslibrary_gsap.md":"2e100eb5","cssstudy_flex.md":"8fa7146f","sunfeistudymysql_sunfeimysql.md":"a5ad502f","vuestudy_vue.md":"d8928238","web3d_three.js.md":"7747081e","mysqlstudy_index.md":"403c5c04"}
